Digital Logic Design/lab2/lab_2b.v
`timescale 10ns/1ns
 module project_2A;

  
    reg A=0, B=0, C=0, D = 0;
    wire F;

    assign F = (!A && C) || (A && !D);

    initial begin
        $dumpfile ("project_2B.vcd");
        $dumpvars(1,A,B,C,D,F);
        #16;
        $finish();
    end

    always #8 A = ~A;
    always #4 B = ~B;
    always #2 C = ~C;
    always #1 D = ~D;
 endmodule

Digital Logic Design/lab2/project_2B.vcd
$date
	Mon Jan 29 18:30:07 2024
$end
$version
	Icarus Verilog
$end
$timescale
	1ns
$end
$scope module project_2A $end
$var reg 1 ! A $end
$upscope $end
$scope module project_2A $end
$var reg 1 " B $end
$upscope $end
$scope module project_2A $end
$var reg 1 # C $end
$upscope $end
$scope module project_2A $end
$var reg 1 $ D $end
$upscope $end
$scope module project_2A $end
$var wire 1 % F $end
$upscope $end
$enddefinitions $end
#0
$dumpvars
0%
0$
0#
0"
0!
$end
#10
1$
#20
1%
0$
1#
#30
1$
#40
0%
0$
0#
1"
#50
1$
#60
1%
0$
1#
#70
1$
#80
0$
0#
0"
1!
#90
0%
1$
#100
1%
0$
1#
#110
0%
1$
#120
1%
0$
0#
1"
#130
0%
1$
#140
1%
0$
1#
#150
0%
1$
#160
0$
0#
0"
0!
